neoscrypt.cp36-win32.pyd
neoscrypt_python-1.0.3.dist-info/COPYING
neoscrypt_python-1.0.3.dist-info/LICENSE.txt
neoscrypt_python-1.0.3.dist-info/METADATA
neoscrypt_python-1.0.3.dist-info/WHEEL
neoscrypt_python-1.0.3.dist-info/top_level.txt
neoscrypt_python-1.0.3.dist-info/RECORD
